slipsomat/__init__.py
slipsomat/shell.py
slipsomat/slipsomat.py
slipsomat/worker.py
slipsomat-0.3.1.dist-info/LICENSE
slipsomat-0.3.1.dist-info/METADATA
slipsomat-0.3.1.dist-info/WHEEL
slipsomat-0.3.1.dist-info/entry_points.txt
slipsomat-0.3.1.dist-info/top_level.txt
slipsomat-0.3.1.dist-info/RECORD
