Metadata-Version: 2.1
Name: slipsomat
Version: 0.3.1
Summary: Sync Alma slips & letters
Home-page: https://github.com/scriptotek/alma-slipsomat
Author: Dan Michael O. Heggø
Author-email: d.m.heggo@ub.uio.no
License: MIT
Keywords: alma browser-automation
Platform: UNKNOWN
Classifier: Programming Language :: Python
Classifier: Programming Language :: Python :: 3.5
Classifier: Programming Language :: Python :: 3.6
Classifier: Programming Language :: Python :: 3.7
Requires-Dist: selenium
Requires-Dist: colorama
Requires-Dist: python-dateutil
Requires-Dist: questionary
